dictum_backend_vertica/__init__.py
dictum_backend_vertica/prefix.py
dictum_backend_vertica/vertica_backend.py
dictum_backend_vertica-0.1.5.dist-info/entry_points.txt
dictum_backend_vertica-0.1.5.dist-info/LICENSE
dictum_backend_vertica-0.1.5.dist-info/WHEEL
dictum_backend_vertica-0.1.5.dist-info/METADATA
dictum_backend_vertica-0.1.5.dist-info/RECORD
