Metadata-Version: 2.1
Name: dictum-backend-vertica
Version: 0.1.5
Summary: Vertica backend for Dictum
Author: Mikhail Akimov
Requires-Python: >=3.8,<4
Classifier: Programming Language :: Python :: 3
Classifier: Programming Language :: Python :: 3.8
Classifier: Programming Language :: Python :: 3.9
Classifier: Programming Language :: Python :: 3.10
Classifier: Programming Language :: Python :: 3.11
Requires-Dist: dictum-core (>=0.1.2,<0.2.0)
Requires-Dist: sqlalchemy-vertica-python (>=0.5.10,<0.6.0)
